{
  "book": {
    "properties": {
      "_record_link": {
        "type": "string",
        "index": "not_analyzed"
      },
      "_language": {
        "type": "string",
        "index": "not_analyzed",
        "fields": {
          "folded": {
            "type": "string",
            "analyzer": "folding"
          }
        }
      },
      "_grp_type": {
        "type": "string",
        "index": "not_analyzed",
        "fields": {
          "raw": {
            "type": "string",
            "index": "not_analyzed"
          }
        }
      },
      "_ingest_date": {
        "type": "date"
      },
      "_title_display": {
        "type": "string",
        "fields": {
          "sort": {
            "type": "string",
            "analyzer": "sortable"
          },
          "folded": {
            "type": "string",
            "analyzer": "folding"
          }
        }
      },
      "_subject_facets": {
        "type": "string",
        "fields": {
          "raw": {
            "type": "string",
            "index": "not_analyzed"
          },
          "folded": {
            "type": "string",
            "analyzer": "folding"
          }
        }
      },
      "_creator_display": {
        "type": "string",
        "index": "not_analyzed",
        "fields": {
          "folded": {
            "type": "string",
            "analyzer": "folding"
          }
        }
      },
      "_creator_facet": {
        "type": "string",
        "fields": {
          "raw": {
            "type": "string",
            "index": "not_analyzed"
          },
          "folded": {
            "type": "string",
            "analyzer": "folding"
          }
        }
      },
      "_date_facet": {
        "type": "date",
        "fields": {
          "folded": {
            "type": "string",
            "analyzer": "folding"
          }
        }
      },
      "_date_display": {
        "type": "string",
        "index": "not_analyzed",
        "fields": {
          "folded": {
            "type": "string",
            "analyzer": "folding"
          }
        }
      },
      "_grp_contributor": {
        "type": "string",
        "fields": {
          "raw": {
            "type": "string",
            "index": "not_analyzed"
          },
          "folded": {
            "type": "string",
            "analyzer": "folding"
          }
        }
      },
      "_grp_id": {
        "type": "string",
        "index": "not_analyzed"
      },
      "_edition": {
        "type": "string",
        "index": "not_analyzed",
        "fields": {
          "folded": {
            "type": "string",
            "analyzer": "folding"
          }
        }
      },
      "_series": {
        "type": "string",
        "index": "not_analyzed",
        "fields": {
          "folded": {
            "type": "string",
            "analyzer": "folding"
          }
        }
      },
      "dublin_core": {
        "type": "object",
        "properties": {
          "identifier": {
            "type": "object",
            "properties":{
              "value": {
                "type": "string",
                "fields": {
                  "folded": {
                    "type": "string",
                    "analyzer": "folding"
                  }
                }
              }
            }
          },
          "creator": {
            "type": "object",
            "properties":{
              "value": {
                "type": "string",
                "fields": {
                  "folded": {
                    "type": "string",
                    "analyzer": "folding"
                  }
                }
              }
            }
          },
          "date": {
            "type": "object",
            "properties": {
              "value": {
                "type": "string",
                "fields": {
                  "folded": {
                    "type": "string",
                    "analyzer": "folding"
                  }
                }
              }
            }
          },
          "publisher": {
            "type": "object",
            "properties":{
              "value": {
                "type": "string",
                "fields": {
                  "folded": {
                    "type": "string",
                    "analyzer": "folding"
                  }
                }
              }
            }
          },
          "format": {
            "type": "object",
            "properties":{
              "value": {
                "type": "string",
                "fields": {
                  "folded": {
                    "type": "string",
                    "analyzer": "folding"
                  }
                }
              }
            }
          },
          "type": {
            "type": "object",
            "properties":{
              "value": {
                "type": "string",
                "fields": {
                  "folded": {
                    "type": "string",
                    "analyzer": "folding"
                  }
                }
              }
            }
          },
          "description": {
            "type": "object",
            "properties":{
              "value": {
                "type": "string",
                "fields": {
                  "folded": {
                    "type": "string",
                    "analyzer": "folding"
                  }
                }
              }
            }
          },
          "provenance": {
            "type": "object",
            "properties":{
              "value": {
                "type": "string",
                "fields": {
                  "folded": {
                    "type": "string",
                    "analyzer": "folding"
                  }
                }
              }
            }
          },
          "language": {
            "type": "object",
            "properties":{
              "value": {
                "type": "string",
                "fields": {
                  "folded": {
                    "type": "string",
                    "analyzer": "folding"
                  }
                }
              }
            }
          },
          "subject": {
            "type": "object",
            "properties":{
              "value": {
                "type": "string",
                "fields": {
                  "folded": {
                    "type": "string",
                    "analyzer": "folding"
                  }
                }
              }
            }
          },
          "coverage": {
            "type": "object",
            "properties":{
              "value": {
                "type": "string",
                "fields": {
                  "folded": {
                    "type": "string",
                    "analyzer": "folding"
                  }
                }
              }
            }
          },
          "title": {
            "type": "object",
            "properties":{
              "value": {
                "type": "string",
                "fields": {
                  "folded": {
                    "type": "string",
                    "analyzer": "folding"
                  }
                }
              }
            }
          },
          "contributor": {
            "type": "object",
            "properties": {
              "value": {
                "type": "string",
                "fields": {
                  "folded": {
                    "type": "string",
                    "analyzer": "folding"
                  }
                }
              }
            }
          },
          "relation": {
            "type": "object",
            "properties": {
              "value": {
                "type": "string",
                "fields": {
                  "folded": {
                    "type": "string",
                    "analyzer": "folding"
                  }
                }
              }
            }
          },
          "source": {
            "type": "object",
            "properties": {
              "value": {
                "type": "string",
                "fields": {
                  "folded": {
                    "type": "string",
                    "analyzer": "folding"
                  }
                }
              }
            }
          },
          "rights": {
            "type": "object",
            "properties": {
              "value": {
                "type": "string",
                "fields": {
                  "folded": {
                    "type": "string",
                    "analyzer": "folding"
                  }
                }
              }
            }
          },
          "accrualMethod": {
            "type": "object",
            "properties": {
              "value": {
                "type": "string",
                "fields": {
                  "folded": {
                    "type": "string",
                    "analyzer": "folding"
                  }
                }
              }
            }
          },
          "accrualPeriodicity": {
            "type": "object",
            "properties": {
              "value": {
                "type": "string",
                "fields": {
                  "folded": {
                    "type": "string",
                    "analyzer": "folding"
                  }
                }
              }
            }
          },
          "audience": {
            "type": "object",
            "properties": {
              "value": {
                "type": "string",
                "fields": {
                  "folded": {
                    "type": "string",
                    "analyzer": "folding"
                  }
                }
              }
            }
          }
        }
      }
    }
  }
}
