{"_contributor_display": ["García, Francisco Javier", "Heras, imp."], "_ingest_date": "2012-05-31", "_creator_facet": ["García, Francisco Javier", "Heras, imp"], "_subject_facets": ["Álgebra", "Obras anteriores a 1800"], "_date_display": "[s.a.]", "_language": ["English"], "_record_link": "http://hdl.handle.net/10630/3029", "_grp_contributor": "Universidad de Málaga", "dublin_core": {"coverage": [{"qualifier": "spatial", "value": "España Zaragoza"}], "identifier": [{"encoding": "URI", "value": "http://hdl.handle.net/10630/3029"}], "language": [{"value": "English"}], "description": [{"value": "Según Gutiérrez del Caño, el impresor ejerce entre 1780-1800"}, {"value": "Digitalizada en formato pdf"}, {"value": "CCPB000229127-4"}, {"value": "Sign.: []2, A-Z4, 2A-2Z4, 3A-3B4"}], "format": [{"qualifier": "extent", "value": "[[4], 382, [2] 4̆"}], "title": [{"value": "Aritmética especulativa y practica y arte mayor o Algebra"}], "subject": [{"value": "Álgebra - Obras anteriores a 1800"}], "contributor": [{"value": "García, Francisco Javier"}, {"value": "Heras, imp."}], "type": [{"value": "Book"}], "publisher": [{"value": "Zaragoza : En la oficina de Heras"}], "date": [{"qualifier": "issued", "value": "[s.a.]"}, {"qualifier": "available", "value": "2010-05-17T08:24:33Z"}]}, "_title_display": "Aritmética especulativa y practica y arte mayor o Algebra", "_grp_id": "malaga_10630_3029"}