{"date":[{"value":"1896-11-21"}],"description":[{"value":"1896/11/21 (A1896,N36)."}],"type":[{"value":"Text","encoding":"DCMI Type Vocabulary"},{"value":"printed serial"}],"identifier":[{"value":"http://gallica.bnf.fr/ark:/12148/bpt6k63442281","encoding":"URI"}],"format":[{"value":"application/pdf","encoding":"IMT"}],"rights":[{"value":"public domain"}],"title":[{"value":"La Chronique des arts et de la curiosité : supplément à la Gazette des beaux-arts"}],"relation":[{"value":"Notice du catalogue","encoding":"URI","uri":"http://catalogue.bnf.fr/ark:/12148/cb34421972m"},{"value":"http://gallica.bnf.fr/ark:/12148/cb34421972m/date","encoding":"URI","uri":"http://gallica.bnf.fr/ark:/12148/cb34421972m/date"}],"source":[{"value":"Bibliothèque nationale de France, département Littérature et art, V-11793"}],"contributor":[{"value":"Houssaye, Édouard. Directeur de publication"}],"language":[{"value":"French"}],"publisher":[{"value":"Gazette des beaux-arts (Paris)"}]}