{"_contributor_display": ["Exposition internationale (1873", "Vienne). Éditeur scientifique"], "_creator_display": ["Cottier, Maurice (1822-1881 ; peintre)"], "_creator_facet": ["Cottier, Maurice", "Exposition internationale", "Vienne). Éditeur scientifique"], "_date_display": "1875", "_record_link": "http://gallica.bnf.fr/ark:/12148/bpt6k63489315", "_title_display": "Rapport sur les beaux-arts / par M. Maurice Cottier,... ; Exposition universelle de Vienne en 1873. Section française", "_grp_id": "bnf_bpt6k63489315", "_ingest_date": "2015-03-17", "_language": ["French"], "_grp_contributor": "Gallica - Bibliothèque nationale de France", "_date_facet": "1875", "dublin_core": {"title": [{"value": "Rapport sur les beaux-arts / par M. Maurice Cottier,... ; Exposition universelle de Vienne en 1873. Section française"}], "identifier": [{"encoding": "URI", "value": "http://gallica.bnf.fr/ark:/12148/bpt6k63489315"}], "source": [{"value": "Bibliothèque nationale de France, département Littérature et art, V-13767"}], "relation": [{"encoding": "URI", "uri": "http://catalogue.bnf.fr/ark:/12148/cb302772890", "value": "Notice du catalogue"}], "language": [{"value": "French"}], "publisher": [{"value": "Impr. nationale (Paris)"}], "format": [{"qualifier": "extent", "value": "1 vol. (87 p.) ; in-4"}, {"encoding": "IMT", "value": "application/pdf"}], "contributor": [{"value": "Exposition internationale (1873"}, {"value": "Vienne). Éditeur scientifique"}], "type": [{"encoding": "DCMI Type Vocabulary", "value": "Text"}, {"value": "printed monograph"}], "creator": [{"value": "Cottier, Maurice (1822-1881 ; peintre)"}], "date": [{"value": "1875"}], "rights": [{"value": "public domain"}]}}